[
  {
    "cameraId": "DLD1120013000",
    "trsmUtcTime": 1763747427353,
    "objId": "0000019241",
    "trsmDy": 21,
    "itisCd": "1545",
    "trsmYear": "2025",
    "trsmMt": "11",
    "trsmTm": "175027",
    "trsmMs": "353",
    "detcLot": 126.9152388,
    "detcLat": 37.5691337,
    "linkId": "1120005700",
    "sttnId": "13005",
    "rgtrId": "v2x",
    "regDt": "2025-11-21T08:50:27.000+00:00"
  },
  {
    "cameraId": "DLD1120013000",
    "trsmUtcTime": 1763747426352,
    "objId": "0000019241",
    "trsmDy": 21,
    "itisCd": "1545",
    "trsmYear": "2025",
    "trsmMt": "11",
    "trsmTm": "175026",
    "trsmMs": "352",
    "detcLot": 126.9152388,
    "detcLat": 37.5691337,
    "linkId": "1120005700",
    "sttnId": "13005",
    "rgtrId": "v2x",
    "regDt": "2025-11-21T08:50:26.000+00:00"
  },
  {
    "cameraId": "DLD1120013000",
    "trsmUtcTime": 1763747425352,
    "objId": "0000019241",
    "trsmDy": 21,
    "itisCd": "1545",
    "trsmYear": "2025",
    "trsmMt": "11",
    "trsmTm": "175025",
    "trsmMs": "352",
    "detcLot": 126.9152388,
    "detcLat": 37.5691337,
    "linkId": "1120005700",
    "sttnId": "13005",
    "rgtrId": "v2x",
    "regDt": "2025-11-21T08:50:25.000+00:00"
  },
  {
    "cameraId": "DLD1120013000",
    "trsmUtcTime": 1763747424351,
    "objId": "0000019241",
    "trsmDy": 21,
    "itisCd": "1545",
    "trsmYear": "2025",
    "trsmMt": "11",
    "trsmTm": "175024",
    "trsmMs": "351",
    "detcLot": 126.9152388,
    "detcLat": 37.5691337,
    "linkId": "1120005700",
    "sttnId": "13005",
    "rgtrId": "v2x",
    "regDt": "2025-11-21T08:50:24.000+00:00"
  },
  {
    "cameraId": "DLD1120013000",
    "trsmUtcTime": 1.76374742235E+12,
    "objId": "0000019241",
    "trsmDy": 21,
    "itisCd": "1545",
    "trsmYear": "2025",
    "trsmMt": "11",
    "trsmTm": "175022",
    "trsmMs": "350",
    "detcLot": 126.9152388,
    "detcLat": 37.5691337,
    "linkId": "1120005700",
    "sttnId": "13005",
    "rgtrId": "v2x",
    "regDt": "2025-11-21T08:50:22.000+00:00"
  },
  {
    "cameraId": "DLD1120013000",
    "trsmUtcTime": 1763747421349,
    "objId": "0000019241",
    "trsmDy": 21,
    "itisCd": "1545",
    "trsmYear": "2025",
    "trsmMt": "11",
    "trsmTm": "175021",
    "trsmMs": "349",
    "detcLot": 126.9152388,
    "detcLat": 37.5691337,
    "linkId": "1120005700",
    "sttnId": "13005",
    "rgtrId": "v2x",
    "regDt": "2025-11-21T08:50:21.000+00:00"
  },
  {
    "cameraId": "DLD1120013000",
    "trsmUtcTime": 1763747420349,
    "objId": "0000019241",
    "trsmDy": 21,
    "itisCd": "1545",
    "trsmYear": "2025",
    "trsmMt": "11",
    "trsmTm": "175020",
    "trsmMs": "349",
    "detcLot": 126.9152388,
    "detcLat": 37.5691337,
    "linkId": "1120005700",
    "sttnId": "13005",
    "rgtrId": "v2x",
    "regDt": "2025-11-21T08:50:20.000+00:00"
  },
  {
    "cameraId": "DLD1120013000",
    "trsmUtcTime": 1763747419348,
    "objId": "0000019241",
    "trsmDy": 21,
    "itisCd": "1545",
    "trsmYear": "2025",
    "trsmMt": "11",
    "trsmTm": "175019",
    "trsmMs": "348",
    "detcLot": 126.9152388,
    "detcLat": 37.5691337,
    "linkId": "1120005700",
    "sttnId": "13005",
    "rgtrId": "v2x",
    "regDt": "2025-11-21T08:50:19.000+00:00"
  },
  {
    "cameraId": "DLD1120013000",
    "trsmUtcTime": 1763747418347,
    "objId": "0000019241",
    "trsmDy": 21,
    "itisCd": "1545",
    "trsmYear": "2025",
    "trsmMt": "11",
    "trsmTm": "175018",
    "trsmMs": "347",
    "detcLot": 126.9152388,
    "detcLat": 37.5691337,
    "linkId": "1120005700",
    "sttnId": "13005",
    "rgtrId": "v2x",
    "regDt": "2025-11-21T08:50:18.000+00:00"
  },
  {
    "cameraId": "DLD1120013000",
    "trsmUtcTime": 1763747417347,
    "objId": "0000019241",
    "trsmDy": 21,
    "itisCd": "1545",
    "trsmYear": "2025",
    "trsmMt": "11",
    "trsmTm": "175017",
    "trsmMs": "347",
    "detcLot": 126.9152388,
    "detcLat": 37.5691337,
    "linkId": "1120005700",
    "sttnId": "13005",
    "rgtrId": "v2x",
    "regDt": "2025-11-21T08:50:17.000+00:00"
  },
  {
    "cameraId": "DLD1120013000",
    "trsmUtcTime": 1763747416346,
    "objId": "0000019241",
    "trsmDy": 21,
    "itisCd": "1545",
    "trsmYear": "2025",
    "trsmMt": "11",
    "trsmTm": "175016",
    "trsmMs": "346",
    "detcLot": 126.9152388,
    "detcLat": 37.5691337,
    "linkId": "1120005700",
    "sttnId": "13005",
    "rgtrId": "v2x",
    "regDt": "2025-11-21T08:50:16.000+00:00"
  },
  {
    "cameraId": "DLD1120013000",
    "trsmUtcTime": 1763747415346,
    "objId": "0000019241",
    "trsmDy": 21,
    "itisCd": "1545",
    "trsmYear": "2025",
    "trsmMt": "11",
    "trsmTm": "175015",
    "trsmMs": "346",
    "detcLot": 126.9152388,
    "detcLat": 37.5691337,
    "linkId": "1120005700",
    "sttnId": "13005",
    "rgtrId": "v2x",
    "regDt": "2025-11-21T08:50:15.000+00:00"
  },
  {
    "cameraId": "DLD1120013000",
    "trsmUtcTime": 1763747411344,
    "objId": "0000019241",
    "trsmDy": 21,
    "itisCd": "1545",
    "trsmYear": "2025",
    "trsmMt": "11",
    "trsmTm": "175011",
    "trsmMs": "344",
    "detcLot": 126.9152388,
    "detcLat": 37.5691337,
    "linkId": "1120005700",
    "sttnId": "13005",
    "rgtrId": "v2x",
    "regDt": "2025-11-21T08:50:11.000+00:00"
  },
  {
    "cameraId": "DLD1120013000",
    "trsmUtcTime": 1763747410343,
    "objId": "0000019241",
    "trsmDy": 21,
    "itisCd": "1545",
    "trsmYear": "2025",
    "trsmMt": "11",
    "trsmTm": "175010",
    "trsmMs": "343",
    "detcLot": 126.9152388,
    "detcLat": 37.5691337,
    "linkId": "1120005700",
    "sttnId": "13005",
    "rgtrId": "v2x",
    "regDt": "2025-11-21T08:50:10.000+00:00"
  },
  {
    "cameraId": "DLD1120013000",
    "trsmUtcTime": 1763747408342,
    "objId": "0000019241",
    "trsmDy": 21,
    "itisCd": "1545",
    "trsmYear": "2025",
    "trsmMt": "11",
    "trsmTm": "175008",
    "trsmMs": "342",
    "detcLot": 126.9152388,
    "detcLat": 37.5691337,
    "linkId": "1120005700",
    "sttnId": "13005",
    "rgtrId": "v2x",
    "regDt": "2025-11-21T08:50:08.000+00:00"
  },
  {
    "cameraId": "DLD1120013000",
    "trsmUtcTime": 1763747399338,
    "objId": "0000019241",
    "trsmDy": 21,
    "itisCd": "1545",
    "trsmYear": "2025",
    "trsmMt": "11",
    "trsmTm": "174959",
    "trsmMs": "338",
    "detcLot": 126.9152388,
    "detcLat": 37.5691337,
    "linkId": "1120005700",
    "sttnId": "13005",
    "rgtrId": "v2x",
    "regDt": "2025-11-21T08:49:59.000+00:00"
  },
  {
    "cameraId": "DLD1120013000",
    "trsmUtcTime": 1763747398337,
    "objId": "0000019241",
    "trsmDy": 21,
    "itisCd": "1545",
    "trsmYear": "2025",
    "trsmMt": "11",
    "trsmTm": "174958",
    "trsmMs": "337",
    "detcLot": 126.9152388,
    "detcLat": 37.5691337,
    "linkId": "1120005700",
    "sttnId": "13005",
    "rgtrId": "v2x",
    "regDt": "2025-11-21T08:49:58.000+00:00"
  },
  {
    "cameraId": "DLD1120013000",
    "trsmUtcTime": 1763747397336,
    "objId": "0000019241",
    "trsmDy": 21,
    "itisCd": "1545",
    "trsmYear": "2025",
    "trsmMt": "11",
    "trsmTm": "174957",
    "trsmMs": "336",
    "detcLot": 126.9152388,
    "detcLat": 37.5691337,
    "linkId": "1120005700",
    "sttnId": "13005",
    "rgtrId": "v2x",
    "regDt": "2025-11-21T08:49:57.000+00:00"
  },
  {
    "cameraId": "DLD1120013000",
    "trsmUtcTime": 1763747396336,
    "objId": "0000019241",
    "trsmDy": 21,
    "itisCd": "1545",
    "trsmYear": "2025",
    "trsmMt": "11",
    "trsmTm": "174956",
    "trsmMs": "336",
    "detcLot": 126.9152388,
    "detcLat": 37.5691337,
    "linkId": "1120005700",
    "sttnId": "13005",
    "rgtrId": "v2x",
    "regDt": "2025-11-21T08:49:56.000+00:00"
  }
]
