[
  {
    "cameraId": "DLD1120013000",
    "trsmUtcTime": 1765213204033,
    "objId": "0000091750",
    "trsmDy": 8,
    "itisCd": "1545",
    "trsmYear": "2025",
    "trsmMt": "12",
    "trsmTm": "170004",
    "trsmMs": "033",
    "detcLot": 126.9152388,
    "detcLat": 37.5691337,
    "linkId": "1120005700",
    "sttnId": "13005",
    "rgtrId": "v2x",
    "regDt": "2025-12-08T08:00:04.000+00:00"
  },
  {
    "cameraId": "DLD1120013000",
    "trsmUtcTime": 1765213203033,
    "objId": "0000091750",
    "trsmDy": 8,
    "itisCd": "1545",
    "trsmYear": "2025",
    "trsmMt": "12",
    "trsmTm": "170003",
    "trsmMs": "033",
    "detcLot": 126.9152388,
    "detcLat": 37.5691337,
    "linkId": "1120005700",
    "sttnId": "13005",
    "rgtrId": "v2x",
    "regDt": "2025-12-08T08:00:04.000+00:00"
  },
  {
    "cameraId": "DLD1120013000",
    "trsmUtcTime": 1765213182026,
    "objId": "0000091694",
    "trsmDy": 8,
    "itisCd": "1545",
    "trsmYear": "2025",
    "trsmMt": "12",
    "trsmTm": "165942",
    "trsmMs": "026",
    "detcLot": 126.9152388,
    "detcLat": 37.5691337,
    "linkId": "1120005700",
    "sttnId": "13005",
    "rgtrId": "v2x",
    "regDt": "2025-12-08T07:59:42.000+00:00"
  },
  {
    "cameraId": "DLD1120013000",
    "trsmUtcTime": 1765213180025,
    "objId": "0000091687",
    "trsmDy": 8,
    "itisCd": "1545",
    "trsmYear": "2025",
    "trsmMt": "12",
    "trsmTm": "165940",
    "trsmMs": "025",
    "detcLot": 126.9152388,
    "detcLat": 37.5691337,
    "linkId": "1120005700",
    "sttnId": "13005",
    "rgtrId": "v2x",
    "regDt": "2025-12-08T07:59:40.000+00:00"
  },
  {
    "cameraId": "DLD1120013000",
    "trsmUtcTime": 1765213179024,
    "objId": "0000091597",
    "trsmDy": 8,
    "itisCd": "1545",
    "trsmYear": "2025",
    "trsmMt": "12",
    "trsmTm": "165939",
    "trsmMs": "024",
    "detcLot": 126.9152388,
    "detcLat": 37.5691337,
    "linkId": "1120005700",
    "sttnId": "13005",
    "rgtrId": "v2x",
    "regDt": "2025-12-08T07:59:40.000+00:00"
  },
  {
    "cameraId": "DLD1120013000",
    "trsmUtcTime": 1765213178024,
    "objId": "0000091597",
    "trsmDy": 8,
    "itisCd": "1545",
    "trsmYear": "2025",
    "trsmMt": "12",
    "trsmTm": "165938",
    "trsmMs": "024",
    "detcLot": 126.9152388,
    "detcLat": 37.5691337,
    "linkId": "1120005700",
    "sttnId": "13005",
    "rgtrId": "v2x",
    "regDt": "2025-12-08T07:59:38.000+00:00"
  },
  {
    "cameraId": "DLD1120013000",
    "trsmUtcTime": 1765213177024,
    "objId": "0000091597",
    "trsmDy": 8,
    "itisCd": "1545",
    "trsmYear": "2025",
    "trsmMt": "12",
    "trsmTm": "165937",
    "trsmMs": "024",
    "detcLot": 126.9152388,
    "detcLat": 37.5691337,
    "linkId": "1120005700",
    "sttnId": "13005",
    "rgtrId": "v2x",
    "regDt": "2025-12-08T07:59:38.000+00:00"
  },
  {
    "cameraId": "DLD1120013000",
    "trsmUtcTime": 1765213175022,
    "objId": "0000091597",
    "trsmDy": 8,
    "itisCd": "1545",
    "trsmYear": "2025",
    "trsmMt": "12",
    "trsmTm": "165935",
    "trsmMs": "022",
    "detcLot": 126.9152388,
    "detcLat": 37.5691337,
    "linkId": "1120005700",
    "sttnId": "13005",
    "rgtrId": "v2x",
    "regDt": "2025-12-08T07:59:36.000+00:00"
  }
]
