[
  {
    "cameraId": "DLD1120013000",
    "trsmUtcTime": 1763726120945,
    "objId": "0000041007",
    "trsmDy": 21,
    "itisCd": "1545",
    "trsmYear": "2025",
    "trsmMt": "11",
    "trsmTm": "115520",
    "trsmMs": "945",
    "detcLot": 126.9152388,
    "detcLat": 37.5691337,
    "linkId": "1120005700",
    "sttnId": "13005",
    "rgtrId": "v2x",
    "regDt": "2025-11-21T02:55:20.000+00:00"
  },
  {
    "cameraId": "DLD1120013000",
    "trsmUtcTime": 1763726119945,
    "objId": "0000041007",
    "trsmDy": 21,
    "itisCd": "1546",
    "trsmYear": "2025",
    "trsmMt": "11",
    "trsmTm": "115519",
    "trsmMs": "945",
    "detcLot": 126.9152388,
    "detcLat": 37.5691337,
    "linkId": "1120005700",
    "sttnId": "13005",
    "rgtrId": "v2x",
    "regDt": "2025-11-21T02:55:19.000+00:00"
  },
  {
    "cameraId": "DLD1120013000",
    "trsmUtcTime": 1763726118944,
    "objId": "0000041007",
    "trsmDy": 21,
    "itisCd": "1546",
    "trsmYear": "2025",
    "trsmMt": "11",
    "trsmTm": "115518",
    "trsmMs": "944",
    "detcLot": 126.9152388,
    "detcLat": 37.5691337,
    "linkId": "1120005700",
    "sttnId": "13005",
    "rgtrId": "v2x",
    "regDt": "2025-11-21T02:55:18.000+00:00"
  },
  {
    "cameraId": "DLD1120013000",
    "trsmUtcTime": 1763726117944,
    "objId": "0000041007",
    "trsmDy": 21,
    "itisCd": "1546",
    "trsmYear": "2025",
    "trsmMt": "11",
    "trsmTm": "115517",
    "trsmMs": "944",
    "detcLot": 126.9152388,
    "detcLat": 37.5691337,
    "linkId": "1120005700",
    "sttnId": "13005",
    "rgtrId": "v2x",
    "regDt": "2025-11-21T02:55:17.000+00:00"
  },
  {
    "cameraId": "DLD1120013000",
    "trsmUtcTime": 1763726116943,
    "objId": "0000041007",
    "trsmDy": 21,
    "itisCd": "1546",
    "trsmYear": "2025",
    "trsmMt": "11",
    "trsmTm": "115516",
    "trsmMs": "943",
    "detcLot": 126.9152388,
    "detcLat": 37.5691337,
    "linkId": "1120005700",
    "sttnId": "13005",
    "rgtrId": "v2x",
    "regDt": "2025-11-21T02:55:16.000+00:00"
  },
  {
    "cameraId": "DLD1120013000",
    "trsmUtcTime": 1763726115943,
    "objId": "0000041007",
    "trsmDy": 21,
    "itisCd": "1546",
    "trsmYear": "2025",
    "trsmMt": "11",
    "trsmTm": "115515",
    "trsmMs": "943",
    "detcLot": 126.9152388,
    "detcLat": 37.5691337,
    "linkId": "1120005700",
    "sttnId": "13005",
    "rgtrId": "v2x",
    "regDt": "2025-11-21T02:55:15.000+00:00"
  },
  {
    "cameraId": "DLD1120013000",
    "trsmUtcTime": 1763726114942,
    "objId": "0000041007",
    "trsmDy": 21,
    "itisCd": "1545",
    "trsmYear": "2025",
    "trsmMt": "11",
    "trsmTm": "115514",
    "trsmMs": "942",
    "detcLot": 126.9152388,
    "detcLat": 37.5691337,
    "linkId": "1120005700",
    "sttnId": "13005",
    "rgtrId": "v2x",
    "regDt": "2025-11-21T02:55:14.000+00:00"
  },
  {
    "cameraId": "DLD1120013000",
    "trsmUtcTime": 1763726113941,
    "objId": "0000041007",
    "trsmDy": 21,
    "itisCd": "1545",
    "trsmYear": "2025",
    "trsmMt": "11",
    "trsmTm": "115513",
    "trsmMs": "941",
    "detcLot": 126.9152388,
    "detcLat": 37.5691337,
    "linkId": "1120005700",
    "sttnId": "13005",
    "rgtrId": "v2x",
    "regDt": "2025-11-21T02:55:13.000+00:00"
  },
  {
    "cameraId": "DLD1120013000",
    "trsmUtcTime": 1.76372611294E+12,
    "objId": "0000041007",
    "trsmDy": 21,
    "itisCd": "1545",
    "trsmYear": "2025",
    "trsmMt": "11",
    "trsmTm": "115512",
    "trsmMs": "940",
    "detcLot": 126.9152388,
    "detcLat": 37.5691337,
    "linkId": "1120005700",
    "sttnId": "13005",
    "rgtrId": "v2x",
    "regDt": "2025-11-21T02:55:12.000+00:00"
  },
  {
    "cameraId": "DLD1120013000",
    "trsmUtcTime": 1763726111939,
    "objId": "0000041007",
    "trsmDy": 21,
    "itisCd": "1545",
    "trsmYear": "2025",
    "trsmMt": "11",
    "trsmTm": "115511",
    "trsmMs": "939",
    "detcLot": 126.9152388,
    "detcLat": 37.5691337,
    "linkId": "1120005700",
    "sttnId": "13005",
    "rgtrId": "v2x",
    "regDt": "2025-11-21T02:55:12.000+00:00"
  },
  {
    "cameraId": "DLD1120013000",
    "trsmUtcTime": 1763726110938,
    "objId": "0000041007",
    "trsmDy": 21,
    "itisCd": "1545",
    "trsmYear": "2025",
    "trsmMt": "11",
    "trsmTm": "115510",
    "trsmMs": "938",
    "detcLot": 126.9152388,
    "detcLat": 37.5691337,
    "linkId": "1120005700",
    "sttnId": "13005",
    "rgtrId": "v2x",
    "regDt": "2025-11-21T02:55:10.000+00:00"
  },
  {
    "cameraId": "DLD1120013000",
    "trsmUtcTime": 1763726108938,
    "objId": "0000041007",
    "trsmDy": 21,
    "itisCd": "1545",
    "trsmYear": "2025",
    "trsmMt": "11",
    "trsmTm": "115508",
    "trsmMs": "938",
    "detcLot": 126.9152388,
    "detcLat": 37.5691337,
    "linkId": "1120005700",
    "sttnId": "13005",
    "rgtrId": "v2x",
    "regDt": "2025-11-21T02:55:08.000+00:00"
  },
  {
    "cameraId": "DLD1120013000",
    "trsmUtcTime": 1763726107937,
    "objId": "0000041007",
    "trsmDy": 21,
    "itisCd": "1545",
    "trsmYear": "2025",
    "trsmMt": "11",
    "trsmTm": "115507",
    "trsmMs": "937",
    "detcLot": 126.9152388,
    "detcLat": 37.5691337,
    "linkId": "1120005700",
    "sttnId": "13005",
    "rgtrId": "v2x",
    "regDt": "2025-11-21T02:55:07.000+00:00"
  },
  {
    "cameraId": "DLD1120013000",
    "trsmUtcTime": 1763726106936,
    "objId": "0000041007",
    "trsmDy": 21,
    "itisCd": "1545",
    "trsmYear": "2025",
    "trsmMt": "11",
    "trsmTm": "115506",
    "trsmMs": "936",
    "detcLot": 126.9152388,
    "detcLat": 37.5691337,
    "linkId": "1120005700",
    "sttnId": "13005",
    "rgtrId": "v2x",
    "regDt": "2025-11-21T02:55:06.000+00:00"
  },
  {
    "cameraId": "DLD1120013000",
    "trsmUtcTime": 1763726105936,
    "objId": "0000041007",
    "trsmDy": 21,
    "itisCd": "1545",
    "trsmYear": "2025",
    "trsmMt": "11",
    "trsmTm": "115505",
    "trsmMs": "936",
    "detcLot": 126.9152388,
    "detcLat": 37.5691337,
    "linkId": "1120005700",
    "sttnId": "13005",
    "rgtrId": "v2x",
    "regDt": "2025-11-21T02:55:05.000+00:00"
  },
  {
    "cameraId": "DLD1120013000",
    "trsmUtcTime": 1763726104935,
    "objId": "0000041007",
    "trsmDy": 21,
    "itisCd": "1545",
    "trsmYear": "2025",
    "trsmMt": "11",
    "trsmTm": "115504",
    "trsmMs": "935",
    "detcLot": 126.9152388,
    "detcLat": 37.5691337,
    "linkId": "1120005700",
    "sttnId": "13005",
    "rgtrId": "v2x",
    "regDt": "2025-11-21T02:55:04.000+00:00"
  },
  {
    "cameraId": "DLD1120013000",
    "trsmUtcTime": 1763726103935,
    "objId": "0000041007",
    "trsmDy": 21,
    "itisCd": "1545",
    "trsmYear": "2025",
    "trsmMt": "11",
    "trsmTm": "115503",
    "trsmMs": "935",
    "detcLot": 126.9152388,
    "detcLat": 37.5691337,
    "linkId": "1120005700",
    "sttnId": "13005",
    "rgtrId": "v2x",
    "regDt": "2025-11-21T02:55:03.000+00:00"
  },
  {
    "cameraId": "DLD1120013000",
    "trsmUtcTime": 1763726102934,
    "objId": "0000041007",
    "trsmDy": 21,
    "itisCd": "1545",
    "trsmYear": "2025",
    "trsmMt": "11",
    "trsmTm": "115502",
    "trsmMs": "934",
    "detcLot": 126.9152388,
    "detcLat": 37.5691337,
    "linkId": "1120005700",
    "sttnId": "13005",
    "rgtrId": "v2x",
    "regDt": "2025-11-21T02:55:02.000+00:00"
  },
  {
    "cameraId": "DLD1120013000",
    "trsmUtcTime": 1763726101934,
    "objId": "0000041007",
    "trsmDy": 21,
    "itisCd": "1545",
    "trsmYear": "2025",
    "trsmMt": "11",
    "trsmTm": "115501",
    "trsmMs": "934",
    "detcLot": 126.9152388,
    "detcLat": 37.5691337,
    "linkId": "1120005700",
    "sttnId": "13005",
    "rgtrId": "v2x",
    "regDt": "2025-11-21T02:55:01.000+00:00"
  },
  {
    "cameraId": "DLD1120013000",
    "trsmUtcTime": 1763726100933,
    "objId": "0000041007",
    "trsmDy": 21,
    "itisCd": "1545",
    "trsmYear": "2025",
    "trsmMt": "11",
    "trsmTm": "115500",
    "trsmMs": "933",
    "detcLot": 126.9152388,
    "detcLat": 37.5691337,
    "linkId": "1120005700",
    "sttnId": "13005",
    "rgtrId": "v2x",
    "regDt": "2025-11-21T02:55:00.000+00:00"
  },
  {
    "cameraId": "DLD1120013000",
    "trsmUtcTime": 1763726096931,
    "objId": "0000041007",
    "trsmDy": 21,
    "itisCd": "1545",
    "trsmYear": "2025",
    "trsmMt": "11",
    "trsmTm": "115456",
    "trsmMs": "931",
    "detcLot": 126.9152388,
    "detcLat": 37.5691337,
    "linkId": "1120005700",
    "sttnId": "13005",
    "rgtrId": "v2x",
    "regDt": "2025-11-21T02:54:56.000+00:00"
  },
  {
    "cameraId": "DLD1120013000",
    "trsmUtcTime": 1.76372609493E+12,
    "objId": "0000041007",
    "trsmDy": 21,
    "itisCd": "1545",
    "trsmYear": "2025",
    "trsmMt": "11",
    "trsmTm": "115454",
    "trsmMs": "930",
    "detcLot": 126.9152388,
    "detcLat": 37.5691337,
    "linkId": "1120005700",
    "sttnId": "13005",
    "rgtrId": "v2x",
    "regDt": "2025-11-21T02:54:54.000+00:00"
  },
  {
    "cameraId": "DLD1120013000",
    "trsmUtcTime": 1763726092929,
    "objId": "0000041007",
    "trsmDy": 21,
    "itisCd": "1545",
    "trsmYear": "2025",
    "trsmMt": "11",
    "trsmTm": "115452",
    "trsmMs": "929",
    "detcLot": 126.9152388,
    "detcLat": 37.5691337,
    "linkId": "1120005700",
    "sttnId": "13005",
    "rgtrId": "v2x",
    "regDt": "2025-11-21T02:54:52.000+00:00"
  }
]
