[
  {
    "cameraId": "DLD1120013000",
    "trsmUtcTime": 1764082292546,
    "objId": "0000040161",
    "trsmDy": 25,
    "itisCd": "1545",
    "trsmYear": "2025",
    "trsmMt": "11",
    "trsmTm": "145132",
    "trsmMs": "546",
    "detcLot": 126.9152388,
    "detcLat": 37.5691337,
    "linkId": "1120005700",
    "sttnId": "13005",
    "rgtrId": "v2x",
    "regDt": "2025-11-25T05:51:32.000+00:00"
  },
  {
    "cameraId": "DLD1120013000",
    "trsmUtcTime": 1764082291545,
    "objId": "0000040161",
    "trsmDy": 25,
    "itisCd": "1545",
    "trsmYear": "2025",
    "trsmMt": "11",
    "trsmTm": "145131",
    "trsmMs": "545",
    "detcLot": 126.9152388,
    "detcLat": 37.5691337,
    "linkId": "1120005700",
    "sttnId": "13005",
    "rgtrId": "v2x",
    "regDt": "2025-11-25T05:51:31.000+00:00"
  },
  {
    "cameraId": "DLD1120013000",
    "trsmUtcTime": 1764082290545,
    "objId": "0000040161",
    "trsmDy": 25,
    "itisCd": "1545",
    "trsmYear": "2025",
    "trsmMt": "11",
    "trsmTm": "145130",
    "trsmMs": "545",
    "detcLot": 126.9152388,
    "detcLat": 37.5691337,
    "linkId": "1120005700",
    "sttnId": "13005",
    "rgtrId": "v2x",
    "regDt": "2025-11-25T05:51:30.000+00:00"
  },
  {
    "cameraId": "DLD1120013000",
    "trsmUtcTime": 1764082289545,
    "objId": "0000040161",
    "trsmDy": 25,
    "itisCd": "1545",
    "trsmYear": "2025",
    "trsmMt": "11",
    "trsmTm": "145129",
    "trsmMs": "545",
    "detcLot": 126.9152388,
    "detcLat": 37.5691337,
    "linkId": "1120005700",
    "sttnId": "13005",
    "rgtrId": "v2x",
    "regDt": "2025-11-25T05:51:29.000+00:00"
  },
  {
    "cameraId": "DLD1120013000",
    "trsmUtcTime": 1764082288544,
    "objId": "0000040161",
    "trsmDy": 25,
    "itisCd": "1545",
    "trsmYear": "2025",
    "trsmMt": "11",
    "trsmTm": "145128",
    "trsmMs": "544",
    "detcLot": 126.9152388,
    "detcLat": 37.5691337,
    "linkId": "1120005700",
    "sttnId": "13005",
    "rgtrId": "v2x",
    "regDt": "2025-11-25T05:51:28.000+00:00"
  },
  {
    "cameraId": "DLD1120013000",
    "trsmUtcTime": 1764082286544,
    "objId": "0000040161",
    "trsmDy": 25,
    "itisCd": "1545",
    "trsmYear": "2025",
    "trsmMt": "11",
    "trsmTm": "145126",
    "trsmMs": "544",
    "detcLot": 126.9152388,
    "detcLat": 37.5691337,
    "linkId": "1120005700",
    "sttnId": "13005",
    "rgtrId": "v2x",
    "regDt": "2025-11-25T05:51:26.000+00:00"
  },
  {
    "cameraId": "DLD1120013000",
    "trsmUtcTime": 1764082285543,
    "objId": "0000040161",
    "trsmDy": 25,
    "itisCd": "1545",
    "trsmYear": "2025",
    "trsmMt": "11",
    "trsmTm": "145125",
    "trsmMs": "543",
    "detcLot": 126.9152388,
    "detcLat": 37.5691337,
    "linkId": "1120005700",
    "sttnId": "13005",
    "rgtrId": "v2x",
    "regDt": "2025-11-25T05:51:25.000+00:00"
  },
  {
    "cameraId": "DLD1120013000",
    "trsmUtcTime": 1764082284543,
    "objId": "0000040161",
    "trsmDy": 25,
    "itisCd": "1545",
    "trsmYear": "2025",
    "trsmMt": "11",
    "trsmTm": "145124",
    "trsmMs": "543",
    "detcLot": 126.9152388,
    "detcLat": 37.5691337,
    "linkId": "1120005700",
    "sttnId": "13005",
    "rgtrId": "v2x",
    "regDt": "2025-11-25T05:51:24.000+00:00"
  },
  {
    "cameraId": "DLD1120013000",
    "trsmUtcTime": 1764082283543,
    "objId": "0000040161",
    "trsmDy": 25,
    "itisCd": "1545",
    "trsmYear": "2025",
    "trsmMt": "11",
    "trsmTm": "145123",
    "trsmMs": "543",
    "detcLot": 126.9152388,
    "detcLat": 37.5691337,
    "linkId": "1120005700",
    "sttnId": "13005",
    "rgtrId": "v2x",
    "regDt": "2025-11-25T05:51:23.000+00:00"
  },
  {
    "cameraId": "DLD1120013000",
    "trsmUtcTime": 1764082281542,
    "objId": "0000040161",
    "trsmDy": 25,
    "itisCd": "1545",
    "trsmYear": "2025",
    "trsmMt": "11",
    "trsmTm": "145121",
    "trsmMs": "542",
    "detcLot": 126.9152388,
    "detcLat": 37.5691337,
    "linkId": "1120005700",
    "sttnId": "13005",
    "rgtrId": "v2x",
    "regDt": "2025-11-25T05:51:21.000+00:00"
  },
  {
    "cameraId": "DLD1120013000",
    "trsmUtcTime": 1764082280542,
    "objId": "0000040161",
    "trsmDy": 25,
    "itisCd": "1545",
    "trsmYear": "2025",
    "trsmMt": "11",
    "trsmTm": "145120",
    "trsmMs": "542",
    "detcLot": 126.9152388,
    "detcLat": 37.5691337,
    "linkId": "1120005700",
    "sttnId": "13005",
    "rgtrId": "v2x",
    "regDt": "2025-11-25T05:51:20.000+00:00"
  },
  {
    "cameraId": "DLD1120013000",
    "trsmUtcTime": 1764082279542,
    "objId": "0000040161",
    "trsmDy": 25,
    "itisCd": "1545",
    "trsmYear": "2025",
    "trsmMt": "11",
    "trsmTm": "145119",
    "trsmMs": "542",
    "detcLot": 126.9152388,
    "detcLat": 37.5691337,
    "linkId": "1120005700",
    "sttnId": "13005",
    "rgtrId": "v2x",
    "regDt": "2025-11-25T05:51:19.000+00:00"
  },
  {
    "cameraId": "DLD1120013000",
    "trsmUtcTime": 1764082278541,
    "objId": "0000040161",
    "trsmDy": 25,
    "itisCd": "1546",
    "trsmYear": "2025",
    "trsmMt": "11",
    "trsmTm": "145118",
    "trsmMs": "541",
    "detcLot": 126.9152388,
    "detcLat": 37.5691337,
    "linkId": "1120005700",
    "sttnId": "13005",
    "rgtrId": "v2x",
    "regDt": "2025-11-25T05:51:18.000+00:00"
  },
  {
    "cameraId": "DLD1120013000",
    "trsmUtcTime": 1764082277541,
    "objId": "0000040161",
    "trsmDy": 25,
    "itisCd": "1546",
    "trsmYear": "2025",
    "trsmMt": "11",
    "trsmTm": "145117",
    "trsmMs": "541",
    "detcLot": 126.9152388,
    "detcLat": 37.5691337,
    "linkId": "1120005700",
    "sttnId": "13005",
    "rgtrId": "v2x",
    "regDt": "2025-11-25T05:51:17.000+00:00"
  },
  {
    "cameraId": "DLD1120013000",
    "trsmUtcTime": 1.76408227554E+12,
    "objId": "0000040161",
    "trsmDy": 25,
    "itisCd": "1546",
    "trsmYear": "2025",
    "trsmMt": "11",
    "trsmTm": "145115",
    "trsmMs": "540",
    "detcLot": 126.9152388,
    "detcLat": 37.5691337,
    "linkId": "1120005700",
    "sttnId": "13005",
    "rgtrId": "v2x",
    "regDt": "2025-11-25T05:51:15.000+00:00"
  },
  {
    "cameraId": "DLD1120013000",
    "trsmUtcTime": 1.76408227454E+12,
    "objId": "0000040161",
    "trsmDy": 25,
    "itisCd": "1546",
    "trsmYear": "2025",
    "trsmMt": "11",
    "trsmTm": "145114",
    "trsmMs": "540",
    "detcLot": 126.9152388,
    "detcLat": 37.5691337,
    "linkId": "1120005700",
    "sttnId": "13005",
    "rgtrId": "v2x",
    "regDt": "2025-11-25T05:51:14.000+00:00"
  },
  {
    "cameraId": "DLD1120013000",
    "trsmUtcTime": 1.76408227354E+12,
    "objId": "0000040161",
    "trsmDy": 25,
    "itisCd": "1546",
    "trsmYear": "2025",
    "trsmMt": "11",
    "trsmTm": "145113",
    "trsmMs": "540",
    "detcLot": 126.9152388,
    "detcLat": 37.5691337,
    "linkId": "1120005700",
    "sttnId": "13005",
    "rgtrId": "v2x",
    "regDt": "2025-11-25T05:51:13.000+00:00"
  },
  {
    "cameraId": "DLD1120013000",
    "trsmUtcTime": 1764082272539,
    "objId": "0000040161",
    "trsmDy": 25,
    "itisCd": "1546",
    "trsmYear": "2025",
    "trsmMt": "11",
    "trsmTm": "145112",
    "trsmMs": "539",
    "detcLot": 126.9152388,
    "detcLat": 37.5691337,
    "linkId": "1120005700",
    "sttnId": "13005",
    "rgtrId": "v2x",
    "regDt": "2025-11-25T05:51:12.000+00:00"
  },
  {
    "cameraId": "DLD1120013000",
    "trsmUtcTime": 1764082271539,
    "objId": "0000040161",
    "trsmDy": 25,
    "itisCd": "1546",
    "trsmYear": "2025",
    "trsmMt": "11",
    "trsmTm": "145111",
    "trsmMs": "539",
    "detcLot": 126.9152388,
    "detcLat": 37.5691337,
    "linkId": "1120005700",
    "sttnId": "13005",
    "rgtrId": "v2x",
    "regDt": "2025-11-25T05:51:11.000+00:00"
  },
  {
    "cameraId": "DLD1120013000",
    "trsmUtcTime": 1764082270539,
    "objId": "0000040161",
    "trsmDy": 25,
    "itisCd": "1546",
    "trsmYear": "2025",
    "trsmMt": "11",
    "trsmTm": "145110",
    "trsmMs": "539",
    "detcLot": 126.9152388,
    "detcLat": 37.5691337,
    "linkId": "1120005700",
    "sttnId": "13005",
    "rgtrId": "v2x",
    "regDt": "2025-11-25T05:51:10.000+00:00"
  },
  {
    "cameraId": "DLD1120013000",
    "trsmUtcTime": 1764082268538,
    "objId": "0000040161",
    "trsmDy": 25,
    "itisCd": "1546",
    "trsmYear": "2025",
    "trsmMt": "11",
    "trsmTm": "145108",
    "trsmMs": "538",
    "detcLot": 126.9152388,
    "detcLat": 37.5691337,
    "linkId": "1120005700",
    "sttnId": "13005",
    "rgtrId": "v2x",
    "regDt": "2025-11-25T05:51:08.000+00:00"
  },
  {
    "cameraId": "DLD1120013000",
    "trsmUtcTime": 1764082267538,
    "objId": "0000040161",
    "trsmDy": 25,
    "itisCd": "1546",
    "trsmYear": "2025",
    "trsmMt": "11",
    "trsmTm": "145107",
    "trsmMs": "538",
    "detcLot": 126.9152388,
    "detcLat": 37.5691337,
    "linkId": "1120005700",
    "sttnId": "13005",
    "rgtrId": "v2x",
    "regDt": "2025-11-25T05:51:07.000+00:00"
  },
  {
    "cameraId": "DLD1120013000",
    "trsmUtcTime": 1764082266537,
    "objId": "0000040161",
    "trsmDy": 25,
    "itisCd": "1546",
    "trsmYear": "2025",
    "trsmMt": "11",
    "trsmTm": "145106",
    "trsmMs": "537",
    "detcLot": 126.9152388,
    "detcLat": 37.5691337,
    "linkId": "1120005700",
    "sttnId": "13005",
    "rgtrId": "v2x",
    "regDt": "2025-11-25T05:51:06.000+00:00"
  },
  {
    "cameraId": "DLD1120013000",
    "trsmUtcTime": 1764082265537,
    "objId": "0000040161",
    "trsmDy": 25,
    "itisCd": "1546",
    "trsmYear": "2025",
    "trsmMt": "11",
    "trsmTm": "145105",
    "trsmMs": "537",
    "detcLot": 126.9152388,
    "detcLat": 37.5691337,
    "linkId": "1120005700",
    "sttnId": "13005",
    "rgtrId": "v2x",
    "regDt": "2025-11-25T05:51:05.000+00:00"
  },
  {
    "cameraId": "DLD1120013000",
    "trsmUtcTime": 1764082264537,
    "objId": "0000040161",
    "trsmDy": 25,
    "itisCd": "1545",
    "trsmYear": "2025",
    "trsmMt": "11",
    "trsmTm": "145104",
    "trsmMs": "537",
    "detcLot": 126.9152388,
    "detcLat": 37.5691337,
    "linkId": "1120005700",
    "sttnId": "13005",
    "rgtrId": "v2x",
    "regDt": "2025-11-25T05:51:04.000+00:00"
  },
  {
    "cameraId": "DLD1120013000",
    "trsmUtcTime": 1764082263536,
    "objId": "0000040161",
    "trsmDy": 25,
    "itisCd": "1545",
    "trsmYear": "2025",
    "trsmMt": "11",
    "trsmTm": "145103",
    "trsmMs": "536",
    "detcLot": 126.9152388,
    "detcLat": 37.5691337,
    "linkId": "1120005700",
    "sttnId": "13005",
    "rgtrId": "v2x",
    "regDt": "2025-11-25T05:51:03.000+00:00"
  },
  {
    "cameraId": "DLD1120013000",
    "trsmUtcTime": 1764082262536,
    "objId": "0000040161",
    "trsmDy": 25,
    "itisCd": "1545",
    "trsmYear": "2025",
    "trsmMt": "11",
    "trsmTm": "145102",
    "trsmMs": "536",
    "detcLot": 126.9152388,
    "detcLat": 37.5691337,
    "linkId": "1120005700",
    "sttnId": "13005",
    "rgtrId": "v2x",
    "regDt": "2025-11-25T05:51:02.000+00:00"
  },
  {
    "cameraId": "DLD1120013000",
    "trsmUtcTime": 1764082261536,
    "objId": "0000040161",
    "trsmDy": 25,
    "itisCd": "1545",
    "trsmYear": "2025",
    "trsmMt": "11",
    "trsmTm": "145101",
    "trsmMs": "536",
    "detcLot": 126.9152388,
    "detcLat": 37.5691337,
    "linkId": "1120005700",
    "sttnId": "13005",
    "rgtrId": "v2x",
    "regDt": "2025-11-25T05:51:01.000+00:00"
  },
  {
    "cameraId": "DLD1120013000",
    "trsmUtcTime": 1764082258535,
    "objId": "0000040161",
    "trsmDy": 25,
    "itisCd": "1545",
    "trsmYear": "2025",
    "trsmMt": "11",
    "trsmTm": "145058",
    "trsmMs": "535",
    "detcLot": 126.9152388,
    "detcLat": 37.5691337,
    "linkId": "1120005700",
    "sttnId": "13005",
    "rgtrId": "v2x",
    "regDt": "2025-11-25T05:50:58.000+00:00"
  }
]
