[
  {
    "cameraId": "DLD1120013000",
    "trsmUtcTime": 1763918483103,
    "objId": "0000078765",
    "trsmDy": 23,
    "itisCd": "1545",
    "trsmYear": "2025",
    "trsmMt": "11",
    "trsmTm": "172123",
    "trsmMs": "103",
    "detcLot": 126.9152388,
    "detcLat": 37.5691337,
    "linkId": "1120005700",
    "sttnId": "13005",
    "rgtrId": "v2x",
    "regDt": "2025-11-23T08:21:23.000+00:00"
  },
  {
    "cameraId": "DLD1120013000",
    "trsmUtcTime": 1763918482103,
    "objId": "0000078765",
    "trsmDy": 23,
    "itisCd": "1545",
    "trsmYear": "2025",
    "trsmMt": "11",
    "trsmTm": "172122",
    "trsmMs": "103",
    "detcLot": 126.9152388,
    "detcLat": 37.5691337,
    "linkId": "1120005700",
    "sttnId": "13005",
    "rgtrId": "v2x",
    "regDt": "2025-11-23T08:21:22.000+00:00"
  },
  {
    "cameraId": "DLD1120013000",
    "trsmUtcTime": 1763918481102,
    "objId": "0000078765",
    "trsmDy": 23,
    "itisCd": "1545",
    "trsmYear": "2025",
    "trsmMt": "11",
    "trsmTm": "172121",
    "trsmMs": "102",
    "detcLot": 126.9152388,
    "detcLat": 37.5691337,
    "linkId": "1120005700",
    "sttnId": "13005",
    "rgtrId": "v2x",
    "regDt": "2025-11-23T08:21:21.000+00:00"
  },
  {
    "cameraId": "DLD1120013000",
    "trsmUtcTime": 1763918480101,
    "objId": "0000078765",
    "trsmDy": 23,
    "itisCd": "1545",
    "trsmYear": "2025",
    "trsmMt": "11",
    "trsmTm": "172120",
    "trsmMs": "101",
    "detcLot": 126.9152388,
    "detcLat": 37.5691337,
    "linkId": "1120005700",
    "sttnId": "13005",
    "rgtrId": "v2x",
    "regDt": "2025-11-23T08:21:20.000+00:00"
  }
]
