[
  {
    "cameraId": "DLD1120013000",
    "trsmUtcTime": 1763225564387,
    "objId": "0000018106",
    "trsmDy": 15,
    "itisCd": "1545",
    "trsmYear": "2025",
    "trsmMt": "11",
    "trsmTm": "165244",
    "trsmMs": "387",
    "detcLot": 126.9152388,
    "detcLat": 37.5691337,
    "linkId": "1120005700",
    "sttnId": "13005",
    "rgtrId": "v2x",
    "regDt": "2025-11-15T07:52:44.000+00:00"
  },
  {
    "cameraId": "DLD1120013000",
    "trsmUtcTime": 1763225563387,
    "objId": "0000018106",
    "trsmDy": 15,
    "itisCd": "1545",
    "trsmYear": "2025",
    "trsmMt": "11",
    "trsmTm": "165243",
    "trsmMs": "387",
    "detcLot": 126.9152388,
    "detcLat": 37.5691337,
    "linkId": "1120005700",
    "sttnId": "13005",
    "rgtrId": "v2x",
    "regDt": "2025-11-15T07:52:43.000+00:00"
  },
  {
    "cameraId": "DLD1120013000",
    "trsmUtcTime": 1763225562387,
    "objId": "0000018106",
    "trsmDy": 15,
    "itisCd": "1546",
    "trsmYear": "2025",
    "trsmMt": "11",
    "trsmTm": "165242",
    "trsmMs": "387",
    "detcLot": 126.9152388,
    "detcLat": 37.5691337,
    "linkId": "1120005700",
    "sttnId": "13005",
    "rgtrId": "v2x",
    "regDt": "2025-11-15T07:52:42.000+00:00"
  },
  {
    "cameraId": "DLD1120013000",
    "trsmUtcTime": 1763225560386,
    "objId": "0000018106",
    "trsmDy": 15,
    "itisCd": "1546",
    "trsmYear": "2025",
    "trsmMt": "11",
    "trsmTm": "165240",
    "trsmMs": "386",
    "detcLot": 126.9152388,
    "detcLat": 37.5691337,
    "linkId": "1120005700",
    "sttnId": "13005",
    "rgtrId": "v2x",
    "regDt": "2025-11-15T07:52:40.000+00:00"
  },
  {
    "cameraId": "DLD1120013000",
    "trsmUtcTime": 1763225559386,
    "objId": "0000018106",
    "trsmDy": 15,
    "itisCd": "1546",
    "trsmYear": "2025",
    "trsmMt": "11",
    "trsmTm": "165239",
    "trsmMs": "386",
    "detcLot": 126.9152388,
    "detcLat": 37.5691337,
    "linkId": "1120005700",
    "sttnId": "13005",
    "rgtrId": "v2x",
    "regDt": "2025-11-15T07:52:39.000+00:00"
  },
  {
    "cameraId": "DLD1120013000",
    "trsmUtcTime": 1763225557385,
    "objId": "0000018106",
    "trsmDy": 15,
    "itisCd": "1545",
    "trsmYear": "2025",
    "trsmMt": "11",
    "trsmTm": "165237",
    "trsmMs": "385",
    "detcLot": 126.9152388,
    "detcLat": 37.5691337,
    "linkId": "1120005700",
    "sttnId": "13005",
    "rgtrId": "v2x",
    "regDt": "2025-11-15T07:52:37.000+00:00"
  },
  {
    "cameraId": "DLD1120013000",
    "trsmUtcTime": 1763225556384,
    "objId": "0000018106",
    "trsmDy": 15,
    "itisCd": "1545",
    "trsmYear": "2025",
    "trsmMt": "11",
    "trsmTm": "165236",
    "trsmMs": "384",
    "detcLot": 126.9152388,
    "detcLat": 37.5691337,
    "linkId": "1120005700",
    "sttnId": "13005",
    "rgtrId": "v2x",
    "regDt": "2025-11-15T07:52:36.000+00:00"
  },
  {
    "cameraId": "DLD1120013000",
    "trsmUtcTime": 1763225554384,
    "objId": "0000018106",
    "trsmDy": 15,
    "itisCd": "1545",
    "trsmYear": "2025",
    "trsmMt": "11",
    "trsmTm": "165234",
    "trsmMs": "384",
    "detcLot": 126.9152388,
    "detcLat": 37.5691337,
    "linkId": "1120005700",
    "sttnId": "13005",
    "rgtrId": "v2x",
    "regDt": "2025-11-15T07:52:34.000+00:00"
  },
  {
    "cameraId": "DLD1120013000",
    "trsmUtcTime": 1763225553383,
    "objId": "0000018106",
    "trsmDy": 15,
    "itisCd": "1545",
    "trsmYear": "2025",
    "trsmMt": "11",
    "trsmTm": "165233",
    "trsmMs": "383",
    "detcLot": 126.9152388,
    "detcLat": 37.5691337,
    "linkId": "1120005700",
    "sttnId": "13005",
    "rgtrId": "v2x",
    "regDt": "2025-11-15T07:52:33.000+00:00"
  },
  {
    "cameraId": "DLD1120013000",
    "trsmUtcTime": 1763225552383,
    "objId": "0000018106",
    "trsmDy": 15,
    "itisCd": "1545",
    "trsmYear": "2025",
    "trsmMt": "11",
    "trsmTm": "165232",
    "trsmMs": "383",
    "detcLot": 126.9152388,
    "detcLat": 37.5691337,
    "linkId": "1120005700",
    "sttnId": "13005",
    "rgtrId": "v2x",
    "regDt": "2025-11-15T07:52:32.000+00:00"
  },
  {
    "cameraId": "DLD1120013000",
    "trsmUtcTime": 1763225550382,
    "objId": "0000018106",
    "trsmDy": 15,
    "itisCd": "1545",
    "trsmYear": "2025",
    "trsmMt": "11",
    "trsmTm": "165230",
    "trsmMs": "382",
    "detcLot": 126.9152388,
    "detcLat": 37.5691337,
    "linkId": "1120005700",
    "sttnId": "13005",
    "rgtrId": "v2x",
    "regDt": "2025-11-15T07:52:30.000+00:00"
  },
  {
    "cameraId": "DLD1120013000",
    "trsmUtcTime": 1763225549382,
    "objId": "0000018106",
    "trsmDy": 15,
    "itisCd": "1545",
    "trsmYear": "2025",
    "trsmMt": "11",
    "trsmTm": "165229",
    "trsmMs": "382",
    "detcLot": 126.9152388,
    "detcLat": 37.5691337,
    "linkId": "1120005700",
    "sttnId": "13005",
    "rgtrId": "v2x",
    "regDt": "2025-11-15T07:52:29.000+00:00"
  },
  {
    "cameraId": "DLD1120013000",
    "trsmUtcTime": 1763225548382,
    "objId": "0000018106",
    "trsmDy": 15,
    "itisCd": "1545",
    "trsmYear": "2025",
    "trsmMt": "11",
    "trsmTm": "165228",
    "trsmMs": "382",
    "detcLot": 126.9152388,
    "detcLat": 37.5691337,
    "linkId": "1120005700",
    "sttnId": "13005",
    "rgtrId": "v2x",
    "regDt": "2025-11-15T07:52:28.000+00:00"
  },
  {
    "cameraId": "DLD1120013000",
    "trsmUtcTime": 1763225546381,
    "objId": "0000018106",
    "trsmDy": 15,
    "itisCd": "1545",
    "trsmYear": "2025",
    "trsmMt": "11",
    "trsmTm": "165226",
    "trsmMs": "381",
    "detcLot": 126.9152388,
    "detcLat": 37.5691337,
    "linkId": "1120005700",
    "sttnId": "13005",
    "rgtrId": "v2x",
    "regDt": "2025-11-15T07:52:26.000+00:00"
  },
  {
    "cameraId": "DLD1120013000",
    "trsmUtcTime": 1763225545381,
    "objId": "0000018106",
    "trsmDy": 15,
    "itisCd": "1545",
    "trsmYear": "2025",
    "trsmMt": "11",
    "trsmTm": "165225",
    "trsmMs": "381",
    "detcLot": 126.9152388,
    "detcLat": 37.5691337,
    "linkId": "1120005700",
    "sttnId": "13005",
    "rgtrId": "v2x",
    "regDt": "2025-11-15T07:52:25.000+00:00"
  }
]
