[
  {
    "cameraId": "DLD1120013000",
    "trsmUtcTime": 1.76530475628E+12,
    "objId": "0000011426",
    "trsmDy": 9,
    "itisCd": "1545",
    "trsmYear": "2025",
    "trsmMt": "12",
    "trsmTm": "182556",
    "trsmMs": "280",
    "detcLot": 126.9152388,
    "detcLat": 37.5691337,
    "linkId": "1120005700",
    "sttnId": "13005",
    "rgtrId": "v2x",
    "regDt": "2025-12-09T09:25:57.000+00:00"
  },
  {
    "cameraId": "DLD1120013000",
    "trsmUtcTime": 1765304755279,
    "objId": "0000011426",
    "trsmDy": 9,
    "itisCd": "1545",
    "trsmYear": "2025",
    "trsmMt": "12",
    "trsmTm": "182555",
    "trsmMs": "279",
    "detcLot": 126.9152388,
    "detcLat": 37.5691337,
    "linkId": "1120005700",
    "sttnId": "13005",
    "rgtrId": "v2x",
    "regDt": "2025-12-09T09:25:57.000+00:00"
  },
  {
    "cameraId": "DLD1120013000",
    "trsmUtcTime": 1765304754279,
    "objId": "0000011426",
    "trsmDy": 9,
    "itisCd": "1545",
    "trsmYear": "2025",
    "trsmMt": "12",
    "trsmTm": "182554",
    "trsmMs": "279",
    "detcLot": 126.9152388,
    "detcLat": 37.5691337,
    "linkId": "1120005700",
    "sttnId": "13005",
    "rgtrId": "v2x",
    "regDt": "2025-12-09T09:25:55.000+00:00"
  },
  {
    "cameraId": "DLD1120013000",
    "trsmUtcTime": 1765304753279,
    "objId": "0000011426",
    "trsmDy": 9,
    "itisCd": "1545",
    "trsmYear": "2025",
    "trsmMt": "12",
    "trsmTm": "182553",
    "trsmMs": "279",
    "detcLot": 126.9152388,
    "detcLat": 37.5691337,
    "linkId": "1120005700",
    "sttnId": "13005",
    "rgtrId": "v2x",
    "regDt": "2025-12-09T09:25:55.000+00:00"
  },
  {
    "cameraId": "DLD1120013000",
    "trsmUtcTime": 1765304751278,
    "objId": "0000011426",
    "trsmDy": 9,
    "itisCd": "1545",
    "trsmYear": "2025",
    "trsmMt": "12",
    "trsmTm": "182551",
    "trsmMs": "278",
    "detcLot": 126.9152388,
    "detcLat": 37.5691337,
    "linkId": "1120005700",
    "sttnId": "13005",
    "rgtrId": "v2x",
    "regDt": "2025-12-09T09:25:52.000+00:00"
  },
  {
    "cameraId": "DLD1120013000",
    "trsmUtcTime": 1765304749276,
    "objId": "0000011426",
    "trsmDy": 9,
    "itisCd": "1545",
    "trsmYear": "2025",
    "trsmMt": "12",
    "trsmTm": "182549",
    "trsmMs": "276",
    "detcLot": 126.9152388,
    "detcLat": 37.5691337,
    "linkId": "1120005700",
    "sttnId": "13005",
    "rgtrId": "v2x",
    "regDt": "2025-12-09T09:25:50.000+00:00"
  },
  {
    "cameraId": "DLD1120013000",
    "trsmUtcTime": 1765304748276,
    "objId": "0000011426",
    "trsmDy": 9,
    "itisCd": "1545",
    "trsmYear": "2025",
    "trsmMt": "12",
    "trsmTm": "182548",
    "trsmMs": "276",
    "detcLot": 126.9152388,
    "detcLat": 37.5691337,
    "linkId": "1120005700",
    "sttnId": "13005",
    "rgtrId": "v2x",
    "regDt": "2025-12-09T09:25:48.000+00:00"
  },
  {
    "cameraId": "DLD1120013000",
    "trsmUtcTime": 1765304747275,
    "objId": "0000011426",
    "trsmDy": 9,
    "itisCd": "1545",
    "trsmYear": "2025",
    "trsmMt": "12",
    "trsmTm": "182547",
    "trsmMs": "275",
    "detcLot": 126.9152388,
    "detcLat": 37.5691337,
    "linkId": "1120005700",
    "sttnId": "13005",
    "rgtrId": "v2x",
    "regDt": "2025-12-09T09:25:48.000+00:00"
  },
  {
    "cameraId": "DLD1120013000",
    "trsmUtcTime": 1765304746275,
    "objId": "0000011426",
    "trsmDy": 9,
    "itisCd": "1545",
    "trsmYear": "2025",
    "trsmMt": "12",
    "trsmTm": "182546",
    "trsmMs": "275",
    "detcLot": 126.9152388,
    "detcLat": 37.5691337,
    "linkId": "1120005700",
    "sttnId": "13005",
    "rgtrId": "v2x",
    "regDt": "2025-12-09T09:25:48.000+00:00"
  },
  {
    "cameraId": "DLD1120013000",
    "trsmUtcTime": 1765304745273,
    "objId": "0000011426",
    "trsmDy": 9,
    "itisCd": "1545",
    "trsmYear": "2025",
    "trsmMt": "12",
    "trsmTm": "182545",
    "trsmMs": "273",
    "detcLot": 126.9152388,
    "detcLat": 37.5691337,
    "linkId": "1120005700",
    "sttnId": "13005",
    "rgtrId": "v2x",
    "regDt": "2025-12-09T09:25:45.000+00:00"
  },
  {
    "cameraId": "DLD1120013000",
    "trsmUtcTime": 1765304744272,
    "objId": "0000011426",
    "trsmDy": 9,
    "itisCd": "1545",
    "trsmYear": "2025",
    "trsmMt": "12",
    "trsmTm": "182544",
    "trsmMs": "272",
    "detcLot": 126.9152388,
    "detcLat": 37.5691337,
    "linkId": "1120005700",
    "sttnId": "13005",
    "rgtrId": "v2x",
    "regDt": "2025-12-09T09:25:45.000+00:00"
  },
  {
    "cameraId": "DLD1120013000",
    "trsmUtcTime": 1765304743271,
    "objId": "0000011426",
    "trsmDy": 9,
    "itisCd": "1545",
    "trsmYear": "2025",
    "trsmMt": "12",
    "trsmTm": "182543",
    "trsmMs": "271",
    "detcLot": 126.9152388,
    "detcLat": 37.5691337,
    "linkId": "1120005700",
    "sttnId": "13005",
    "rgtrId": "v2x",
    "regDt": "2025-12-09T09:25:43.000+00:00"
  },
  {
    "cameraId": "DLD1120013000",
    "trsmUtcTime": 1765304742271,
    "objId": "0000011426",
    "trsmDy": 9,
    "itisCd": "1545",
    "trsmYear": "2025",
    "trsmMt": "12",
    "trsmTm": "182542",
    "trsmMs": "271",
    "detcLot": 126.9152388,
    "detcLat": 37.5691337,
    "linkId": "1120005700",
    "sttnId": "13005",
    "rgtrId": "v2x",
    "regDt": "2025-12-09T09:25:43.000+00:00"
  },
  {
    "cameraId": "DLD1120013000",
    "trsmUtcTime": 1.76530474127E+12,
    "objId": "0000011426",
    "trsmDy": 9,
    "itisCd": "1545",
    "trsmYear": "2025",
    "trsmMt": "12",
    "trsmTm": "182541",
    "trsmMs": "270",
    "detcLot": 126.9152388,
    "detcLat": 37.5691337,
    "linkId": "1120005700",
    "sttnId": "13005",
    "rgtrId": "v2x",
    "regDt": "2025-12-09T09:25:43.000+00:00"
  },
  {
    "cameraId": "DLD1120013000",
    "trsmUtcTime": 1765304740269,
    "objId": "0000011426",
    "trsmDy": 9,
    "itisCd": "1545",
    "trsmYear": "2025",
    "trsmMt": "12",
    "trsmTm": "182540",
    "trsmMs": "269",
    "detcLot": 126.9152388,
    "detcLat": 37.5691337,
    "linkId": "1120005700",
    "sttnId": "13005",
    "rgtrId": "v2x",
    "regDt": "2025-12-09T09:25:40.000+00:00"
  },
  {
    "cameraId": "DLD1120013000",
    "trsmUtcTime": 1765304739267,
    "objId": "0000011426",
    "trsmDy": 9,
    "itisCd": "1545",
    "trsmYear": "2025",
    "trsmMt": "12",
    "trsmTm": "182539",
    "trsmMs": "267",
    "detcLot": 126.9152388,
    "detcLat": 37.5691337,
    "linkId": "1120005700",
    "sttnId": "13005",
    "rgtrId": "v2x",
    "regDt": "2025-12-09T09:25:40.000+00:00"
  },
  {
    "cameraId": "DLD1120013000",
    "trsmUtcTime": 1765304738267,
    "objId": "0000011426",
    "trsmDy": 9,
    "itisCd": "1545",
    "trsmYear": "2025",
    "trsmMt": "12",
    "trsmTm": "182538",
    "trsmMs": "267",
    "detcLot": 126.9152388,
    "detcLat": 37.5691337,
    "linkId": "1120005700",
    "sttnId": "13005",
    "rgtrId": "v2x",
    "regDt": "2025-12-09T09:25:38.000+00:00"
  },
  {
    "cameraId": "DLD1120013000",
    "trsmUtcTime": 1765304736266,
    "objId": "0000011426",
    "trsmDy": 9,
    "itisCd": "1545",
    "trsmYear": "2025",
    "trsmMt": "12",
    "trsmTm": "182536",
    "trsmMs": "266",
    "detcLot": 126.9152388,
    "detcLat": 37.5691337,
    "linkId": "1120005700",
    "sttnId": "13005",
    "rgtrId": "v2x",
    "regDt": "2025-12-09T09:25:36.000+00:00"
  },
  {
    "cameraId": "DLD1120013000",
    "trsmUtcTime": 1765304735265,
    "objId": "0000011426",
    "trsmDy": 9,
    "itisCd": "1545",
    "trsmYear": "2025",
    "trsmMt": "12",
    "trsmTm": "182535",
    "trsmMs": "265",
    "detcLot": 126.9152388,
    "detcLat": 37.5691337,
    "linkId": "1120005700",
    "sttnId": "13005",
    "rgtrId": "v2x",
    "regDt": "2025-12-09T09:25:36.000+00:00"
  },
  {
    "cameraId": "DLD1120013000",
    "trsmUtcTime": 1765304733264,
    "objId": "0000011426",
    "trsmDy": 9,
    "itisCd": "1545",
    "trsmYear": "2025",
    "trsmMt": "12",
    "trsmTm": "182533",
    "trsmMs": "264",
    "detcLot": 126.9152388,
    "detcLat": 37.5691337,
    "linkId": "1120005700",
    "sttnId": "13005",
    "rgtrId": "v2x",
    "regDt": "2025-12-09T09:25:34.000+00:00"
  }
]
