[
  {
    "cameraId": "DLD1120013000",
    "trsmUtcTime": 1764497386425,
    "objId": "0000000860",
    "trsmDy": 30,
    "itisCd": "1545",
    "trsmYear": "2025",
    "trsmMt": "11",
    "trsmTm": "100946",
    "trsmMs": "425",
    "detcLot": 126.9152388,
    "detcLat": 37.5691337,
    "linkId": "1120005700",
    "sttnId": "13005",
    "rgtrId": "v2x",
    "regDt": "2025-11-30T01:09:46.000+00:00"
  },
  {
    "cameraId": "DLD1120013000",
    "trsmUtcTime": 1764497385425,
    "objId": "0000000860",
    "trsmDy": 30,
    "itisCd": "1545",
    "trsmYear": "2025",
    "trsmMt": "11",
    "trsmTm": "100945",
    "trsmMs": "425",
    "detcLot": 126.9152388,
    "detcLat": 37.5691337,
    "linkId": "1120005700",
    "sttnId": "13005",
    "rgtrId": "v2x",
    "regDt": "2025-11-30T01:09:45.000+00:00"
  },
  {
    "cameraId": "DLD1120013000",
    "trsmUtcTime": 1764497382424,
    "objId": "0000000860",
    "trsmDy": 30,
    "itisCd": "1545",
    "trsmYear": "2025",
    "trsmMt": "11",
    "trsmTm": "100942",
    "trsmMs": "424",
    "detcLot": 126.9152388,
    "detcLat": 37.5691337,
    "linkId": "1120005700",
    "sttnId": "13005",
    "rgtrId": "v2x",
    "regDt": "2025-11-30T01:09:42.000+00:00"
  },
  {
    "cameraId": "DLD1120013000",
    "trsmUtcTime": 1764497381424,
    "objId": "0000000860",
    "trsmDy": 30,
    "itisCd": "1545",
    "trsmYear": "2025",
    "trsmMt": "11",
    "trsmTm": "100941",
    "trsmMs": "424",
    "detcLot": 126.9152388,
    "detcLat": 37.5691337,
    "linkId": "1120005700",
    "sttnId": "13005",
    "rgtrId": "v2x",
    "regDt": "2025-11-30T01:09:41.000+00:00"
  },
  {
    "cameraId": "DLD1120013000",
    "trsmUtcTime": 1.76449737042E+12,
    "objId": "0000000860",
    "trsmDy": 30,
    "itisCd": "1545",
    "trsmYear": "2025",
    "trsmMt": "11",
    "trsmTm": "100930",
    "trsmMs": "420",
    "detcLot": 126.9152388,
    "detcLat": 37.5691337,
    "linkId": "1120005700",
    "sttnId": "13005",
    "rgtrId": "v2x",
    "regDt": "2025-11-30T01:09:30.000+00:00"
  },
  {
    "cameraId": "DLD1120013000",
    "trsmUtcTime": 1764497368419,
    "objId": "0000000860",
    "trsmDy": 30,
    "itisCd": "1545",
    "trsmYear": "2025",
    "trsmMt": "11",
    "trsmTm": "100928",
    "trsmMs": "419",
    "detcLot": 126.9152388,
    "detcLat": 37.5691337,
    "linkId": "1120005700",
    "sttnId": "13005",
    "rgtrId": "v2x",
    "regDt": "2025-11-30T01:09:28.000+00:00"
  },
  {
    "cameraId": "DLD1120013000",
    "trsmUtcTime": 1764497366419,
    "objId": "0000000860",
    "trsmDy": 30,
    "itisCd": "1545",
    "trsmYear": "2025",
    "trsmMt": "11",
    "trsmTm": "100926",
    "trsmMs": "419",
    "detcLot": 126.9152388,
    "detcLat": 37.5691337,
    "linkId": "1120005700",
    "sttnId": "13005",
    "rgtrId": "v2x",
    "regDt": "2025-11-30T01:09:26.000+00:00"
  },
  {
    "cameraId": "DLD1120013000",
    "trsmUtcTime": 1764497364418,
    "objId": "0000000860",
    "trsmDy": 30,
    "itisCd": "1545",
    "trsmYear": "2025",
    "trsmMt": "11",
    "trsmTm": "100924",
    "trsmMs": "418",
    "detcLot": 126.9152388,
    "detcLat": 37.5691337,
    "linkId": "1120005700",
    "sttnId": "13005",
    "rgtrId": "v2x",
    "regDt": "2025-11-30T01:09:24.000+00:00"
  },
  {
    "cameraId": "DLD1120013000",
    "trsmUtcTime": 1764497362417,
    "objId": "0000000860",
    "trsmDy": 30,
    "itisCd": "1545",
    "trsmYear": "2025",
    "trsmMt": "11",
    "trsmTm": "100922",
    "trsmMs": "417",
    "detcLot": 126.9152388,
    "detcLat": 37.5691337,
    "linkId": "1120005700",
    "sttnId": "13005",
    "rgtrId": "v2x",
    "regDt": "2025-11-30T01:09:22.000+00:00"
  },
  {
    "cameraId": "DLD1120013000",
    "trsmUtcTime": 1764497361417,
    "objId": "0000000860",
    "trsmDy": 30,
    "itisCd": "1545",
    "trsmYear": "2025",
    "trsmMt": "11",
    "trsmTm": "100921",
    "trsmMs": "417",
    "detcLot": 126.9152388,
    "detcLat": 37.5691337,
    "linkId": "1120005700",
    "sttnId": "13005",
    "rgtrId": "v2x",
    "regDt": "2025-11-30T01:09:21.000+00:00"
  },
  {
    "cameraId": "DLD1120013000",
    "trsmUtcTime": 1764497360417,
    "objId": "0000000860",
    "trsmDy": 30,
    "itisCd": "1545",
    "trsmYear": "2025",
    "trsmMt": "11",
    "trsmTm": "100920",
    "trsmMs": "417",
    "detcLot": 126.9152388,
    "detcLat": 37.5691337,
    "linkId": "1120005700",
    "sttnId": "13005",
    "rgtrId": "v2x",
    "regDt": "2025-11-30T01:09:20.000+00:00"
  },
  {
    "cameraId": "DLD1120013000",
    "trsmUtcTime": 1764497359416,
    "objId": "0000000860",
    "trsmDy": 30,
    "itisCd": "1545",
    "trsmYear": "2025",
    "trsmMt": "11",
    "trsmTm": "100919",
    "trsmMs": "416",
    "detcLot": 126.9152388,
    "detcLat": 37.5691337,
    "linkId": "1120005700",
    "sttnId": "13005",
    "rgtrId": "v2x",
    "regDt": "2025-11-30T01:09:19.000+00:00"
  },
  {
    "cameraId": "DLD1120013000",
    "trsmUtcTime": 1764497358416,
    "objId": "0000000860",
    "trsmDy": 30,
    "itisCd": "1545",
    "trsmYear": "2025",
    "trsmMt": "11",
    "trsmTm": "100918",
    "trsmMs": "416",
    "detcLot": 126.9152388,
    "detcLat": 37.5691337,
    "linkId": "1120005700",
    "sttnId": "13005",
    "rgtrId": "v2x",
    "regDt": "2025-11-30T01:09:18.000+00:00"
  },
  {
    "cameraId": "DLD1120013000",
    "trsmUtcTime": 1764497353414,
    "objId": "0000000860",
    "trsmDy": 30,
    "itisCd": "1545",
    "trsmYear": "2025",
    "trsmMt": "11",
    "trsmTm": "100913",
    "trsmMs": "414",
    "detcLot": 126.9152388,
    "detcLat": 37.5691337,
    "linkId": "1120005700",
    "sttnId": "13005",
    "rgtrId": "v2x",
    "regDt": "2025-11-30T01:09:13.000+00:00"
  },
  {
    "cameraId": "DLD1120013000",
    "trsmUtcTime": 1764497352414,
    "objId": "0000000860",
    "trsmDy": 30,
    "itisCd": "1545",
    "trsmYear": "2025",
    "trsmMt": "11",
    "trsmTm": "100912",
    "trsmMs": "414",
    "detcLot": 126.9152388,
    "detcLat": 37.5691337,
    "linkId": "1120005700",
    "sttnId": "13005",
    "rgtrId": "v2x",
    "regDt": "2025-11-30T01:09:12.000+00:00"
  },
  {
    "cameraId": "DLD1120013000",
    "trsmUtcTime": 1764497349413,
    "objId": "0000000860",
    "trsmDy": 30,
    "itisCd": "1545",
    "trsmYear": "2025",
    "trsmMt": "11",
    "trsmTm": "100909",
    "trsmMs": "413",
    "detcLot": 126.9152388,
    "detcLat": 37.5691337,
    "linkId": "1120005700",
    "sttnId": "13005",
    "rgtrId": "v2x",
    "regDt": "2025-11-30T01:09:09.000+00:00"
  },
  {
    "cameraId": "DLD1120013000",
    "trsmUtcTime": 1764497347413,
    "objId": "0000000860",
    "trsmDy": 30,
    "itisCd": "1545",
    "trsmYear": "2025",
    "trsmMt": "11",
    "trsmTm": "100907",
    "trsmMs": "413",
    "detcLot": 126.9152388,
    "detcLat": 37.5691337,
    "linkId": "1120005700",
    "sttnId": "13005",
    "rgtrId": "v2x",
    "regDt": "2025-11-30T01:09:07.000+00:00"
  },
  {
    "cameraId": "DLD1120013000",
    "trsmUtcTime": 1764497346412,
    "objId": "0000000860",
    "trsmDy": 30,
    "itisCd": "1545",
    "trsmYear": "2025",
    "trsmMt": "11",
    "trsmTm": "100906",
    "trsmMs": "412",
    "detcLot": 126.9152388,
    "detcLat": 37.5691337,
    "linkId": "1120005700",
    "sttnId": "13005",
    "rgtrId": "v2x",
    "regDt": "2025-11-30T01:09:06.000+00:00"
  }
]
