[
  {
    "cameraId": "DLD1120013000",
    "trsmUtcTime": 1764670643548,
    "objId": "0000016896",
    "trsmDy": 2,
    "itisCd": "1545",
    "trsmYear": "2025",
    "trsmMt": "12",
    "trsmTm": "101723",
    "trsmMs": "548",
    "detcLot": 126.9152388,
    "detcLat": 37.5691337,
    "linkId": "1120005700",
    "sttnId": "13005",
    "rgtrId": "v2x",
    "regDt": "2025-12-02T01:17:23.000+00:00"
  },
  {
    "cameraId": "DLD1120013000",
    "trsmUtcTime": 1764670642548,
    "objId": "0000016896",
    "trsmDy": 2,
    "itisCd": "1545",
    "trsmYear": "2025",
    "trsmMt": "12",
    "trsmTm": "101722",
    "trsmMs": "548",
    "detcLot": 126.9152388,
    "detcLat": 37.5691337,
    "linkId": "1120005700",
    "sttnId": "13005",
    "rgtrId": "v2x",
    "regDt": "2025-12-02T01:17:22.000+00:00"
  },
  {
    "cameraId": "DLD1120013000",
    "trsmUtcTime": 1764670640547,
    "objId": "0000016896",
    "trsmDy": 2,
    "itisCd": "1545",
    "trsmYear": "2025",
    "trsmMt": "12",
    "trsmTm": "101720",
    "trsmMs": "547",
    "detcLot": 126.9152388,
    "detcLat": 37.5691337,
    "linkId": "1120005700",
    "sttnId": "13005",
    "rgtrId": "v2x",
    "regDt": "2025-12-02T01:17:20.000+00:00"
  },
  {
    "cameraId": "DLD1120013000",
    "trsmUtcTime": 1764670638547,
    "objId": "0000016896",
    "trsmDy": 2,
    "itisCd": "1545",
    "trsmYear": "2025",
    "trsmMt": "12",
    "trsmTm": "101718",
    "trsmMs": "547",
    "detcLot": 126.9152388,
    "detcLat": 37.5691337,
    "linkId": "1120005700",
    "sttnId": "13005",
    "rgtrId": "v2x",
    "regDt": "2025-12-02T01:17:18.000+00:00"
  },
  {
    "cameraId": "DLD1120013000",
    "trsmUtcTime": 1764670637546,
    "objId": "0000016896",
    "trsmDy": 2,
    "itisCd": "1545",
    "trsmYear": "2025",
    "trsmMt": "12",
    "trsmTm": "101717",
    "trsmMs": "546",
    "detcLot": 126.9152388,
    "detcLat": 37.5691337,
    "linkId": "1120005700",
    "sttnId": "13005",
    "rgtrId": "v2x",
    "regDt": "2025-12-02T01:17:17.000+00:00"
  }
]
